sopel_meetbot/__init__.py
sopel_meetbot/plugin.py
sopel_meetbot-1.1.0.dist-info/licenses/COPYING
sopel_meetbot-1.1.0.dist-info/METADATA
sopel_meetbot-1.1.0.dist-info/WHEEL
sopel_meetbot-1.1.0.dist-info/entry_points.txt
sopel_meetbot-1.1.0.dist-info/top_level.txt
sopel_meetbot-1.1.0.dist-info/RECORD
