Metadata-Version: 2.4
Name: sopel-meetbot
Version: 1.1.0
Summary: The meetbot plugin formerly shipped with Sopel prior to version 8.0.
Author-email: dgw <dgw@technobabbl.es>
License-Expression: EFL-2.0
Project-URL: Homepage, https://github.com/sopel-irc/sopel-meetbot
Project-URL: Bug Tracker, https://github.com/sopel-irc/sopel-meetbot/issues
Keywords: sopel,plugin,bot,irc
Platform: Linux x86, x86-64
Classifier: Intended Audience :: Developers
Classifier: Intended Audience :: System Administrators
Classifier: Topic :: Communications :: Chat :: Internet Relay Chat
Requires-Python: <4,>=3.8
License-File: COPYING
Requires-Dist: sopel>=8.0
Dynamic: license-file
